vicses/viper/__init__.py
vicses.viper-1.1.0.dist-info/DESCRIPTION.rst
vicses.viper-1.1.0.dist-info/METADATA
vicses.viper-1.1.0.dist-info/RECORD
vicses.viper-1.1.0.dist-info/WHEEL
vicses.viper-1.1.0.dist-info/metadata.json
vicses.viper-1.1.0.dist-info/top_level.txt
