Metadata-Version: 2.0
Name: vicses.viper
Version: 1.1.0
Summary: Send VICSES EAS pages via Viper
Home-page: https://github.com/VICSES/Python-Viper
Author: David Tulloh
Author-email: vicsesdev-david@tulloh.id.au
License: AGPL-3+
Keywords: Viper VICSES EAS paging
Platform: UNKNOWN
Classifier: Development Status :: 4 - Beta
Classifier: Environment :: Web Environment
Classifier: Intended Audience :: Developers
Classifier: License :: OSI Approved :: GNU Affero General Public License v3 or later (AGPLv3+)
Classifier: Natural Language :: English
Classifier: Topic :: Communications
Classifier: Programming Language :: Python :: 3
Requires-Dist: requests
